[
 {
  "customer_care_number": "0124-4973838",
  "docstatus": 0,
  "doctype": "Airline",
  "founding_year": 2006,
  "headquarters": "Gurugram, India",
  "modified": "2025-03-17 19:51:01.505440",
  "name": "IndiGo",
  "website": "https://www.goindigo.in/"
 },
 {
  "customer_care_number": "+919606112131",
  "docstatus": 0,
  "doctype": "Airline",
  "founding_year": 2021,
  "headquarters": "Mumbai, India",
  "modified": "2025-03-17 19:52:21.725448",
  "name": "Akasa Air",
  "website": "https://www.akasaair.com"
 },
 {
  "customer_care_number": "+911169329999",
  "docstatus": 0,
  "doctype": "Airline",
  "founding_year": 1932,
  "headquarters": "New Delhi, India",
  "modified": "2025-03-17 19:53:29.519936",
  "name": "Air India",
  "website": "https://www.airindia.com/"
 },
 {
  "customer_care_number": "+255222117500",
  "docstatus": 0,
  "doctype": "Airline",
  "founding_year": 1977,
  "headquarters": "Dar es Salaam",
  "modified": "2025-03-17 19:55:39.609699",
  "name": "Air Tanzania",
  "website": "https://www.airtanzania.co.tz/"
 }
]